MANIFEST.in
README.rst
requirements.txt
setup.py
examples/plot_cluster_comparison.py
examples/plot_hdbscan.py
hdbscan/__init__.py
hdbscan/_hdbscan_boruvka.c
hdbscan/_hdbscan_boruvka.pyx
hdbscan/_hdbscan_linkage.c
hdbscan/_hdbscan_linkage.pyx
hdbscan/_hdbscan_reachability.c
hdbscan/_hdbscan_reachability.pyx
hdbscan/_hdbscan_tree.c
hdbscan/_hdbscan_tree.pyx
hdbscan/dist_metrics.c
hdbscan/dist_metrics.pxd
hdbscan/dist_metrics.pyx
hdbscan/hdbscan_.py
hdbscan/plots.py
hdbscan/robust_single_linkage_.py
hdbscan/tests/__init__.py
hdbscan/tests/test_hdbscan.py
hdbscan/tests/test_rsl.py
hdbscan_with_cosine_distance.egg-info/PKG-INFO
hdbscan_with_cosine_distance.egg-info/SOURCES.txt
hdbscan_with_cosine_distance.egg-info/dependency_links.txt
hdbscan_with_cosine_distance.egg-info/requires.txt
hdbscan_with_cosine_distance.egg-info/top_level.txt
notebooks/Benchmarking scalability of clustering implementations 2D v0.7.ipynb
notebooks/Benchmarking scalability of clustering implementations-v0.7.ipynb
notebooks/Comparing Clustering Algorithms.ipynb
notebooks/How HDBSCAN Works.ipynb
notebooks/Performance data generation .ipynb
notebooks/Python vs Java.ipynb
notebooks/clusterable_data.npy
notebooks/distance1.svg
notebooks/distance2.svg
notebooks/distance3.svg
notebooks/distance4.svg
notebooks/distance4a.svg
notebooks/distance5.svg