Metadata-Version: 1.1
Name: hdbscan-with-cosine-distance
Version: 0.8.1
Summary: Clustering based on density with variable density clusters
Home-page: http://github.com/lmcinnes/hdbscan
Author: Leland McInnes
Author-email: leland.mcinnes@gmail.com
License: BSD
Keywords: cluster clustering density hierarchical
Platform: UNKNOWN
Classifier: Development Status :: 4 - Beta
Classifier: Intended Audience :: Science/Research
Classifier: Intended Audience :: Developers
Classifier: License :: OSI Approved
Classifier: Programming Language :: C
Classifier: Programming Language :: Python
Classifier: Topic :: Software Development
Classifier: Topic :: Scientific/Engineering
Classifier: Operating System :: Microsoft :: Windows
Classifier: Operating System :: POSIX
Classifier: Operating System :: Unix
Classifier: Operating System :: MacOS
Classifier: Programming Language :: Python :: 2.7
Classifier: Programming Language :: Python :: 3.4
